flockos/__init__.py
flockos/api_client.py
flockos/event_handler_client.py
flockos/token_verifier_filter.py
flockos/utils.py
flockos/apis/__init__.py
flockos/apis/channels.py
flockos/apis/chat.py
flockos/apis/roster.py
flockos/apis/users.py
flockos/models/__init__.py
flockos/models/action_config.py
flockos/models/attachment.py
flockos/models/attachment_button.py
flockos/models/attachment_download.py
flockos/models/channel.py
flockos/models/channel_member.py
flockos/models/error.py
flockos/models/html_view.py
flockos/models/image.py
flockos/models/image_view.py
flockos/models/message.py
flockos/models/public_profile.py
flockos/models/send_as.py
flockos/models/uid_response.py
flockos/models/user.py
flockos/models/views.py
flockos/models/widget_view.py
flockos-1.2.0.dist-info/DESCRIPTION.rst
flockos-1.2.0.dist-info/METADATA
flockos-1.2.0.dist-info/RECORD
flockos-1.2.0.dist-info/WHEEL
flockos-1.2.0.dist-info/metadata.json
flockos-1.2.0.dist-info/top_level.txt
test/__init__.py
test/test_action_config.py
test/test_attachment.py
test/test_attachment_button.py
test/test_attachment_download.py
test/test_chat.py
test/test_error.py
test/test_group.py
test/test_groups.py
test/test_html_view.py
test/test_image.py
test/test_image_view.py
test/test_message.py
test/test_public_profile.py
test/test_roster.py
test/test_send_as.py
test/test_uid_response.py
test/test_user.py
test/test_users.py
test/test_views.py
test/test_widget_view.py
