Metadata-Version: 2.0
Name: flockos
Version: 1.2.0
Summary: Flock API
Home-page: UNKNOWN
Author: UNKNOWN
Author-email: UNKNOWN
License: UNKNOWN
Keywords: Flock API
Platform: UNKNOWN
Requires-Dist: PyJWT
Requires-Dist: requests
Requires-Dist: six (>=1.10)
